batch_tensorsolve/__init__.py
batch_tensorsolve/_main.py
batch_tensorsolve/py.typed
batch_tensorsolve-1.0.1.dist-info/licenses/LICENSE
batch_tensorsolve-1.0.1.dist-info/METADATA
batch_tensorsolve-1.0.1.dist-info/WHEEL
batch_tensorsolve-1.0.1.dist-info/top_level.txt
batch_tensorsolve-1.0.1.dist-info/RECORD
